safedata_validator/__init__.py
safedata_validator/entry_points.py
safedata_validator/extent.py
safedata_validator/field.py
safedata_validator/locations.py
safedata_validator/logger.py
safedata_validator/resources.py
safedata_validator/server.py
safedata_validator/summary.py
safedata_validator/taxa.py
safedata_validator/taxondb.py
safedata_validator/templates/description_template.html
safedata_validator/templates/gemini_xml_template.xml
safedata_validator/utilities.py
safedata_validator/validators.py
safedata_validator/zenodo.py
safedata_validator-3.0.1.dist-info/LICENCE
safedata_validator-3.0.1.dist-info/METADATA
safedata_validator-3.0.1.dist-info/WHEEL
safedata_validator-3.0.1.dist-info/entry_points.txt
safedata_validator-3.0.1.dist-info/RECORD
